sczpy.py
sczpy-0.0.8.dist-info/LICENSE.txt
sczpy-0.0.8.dist-info/METADATA
sczpy-0.0.8.dist-info/NOTICE.txt
sczpy-0.0.8.dist-info/WHEEL
sczpy-0.0.8.dist-info/top_level.txt
sczpy-0.0.8.dist-info/RECORD
