Metadata-Version: 2.1
Name: sczpy
Version: 0.0.8
Summary: Azure Percept Model Management Python SDK
Home-page: https://github.com/microsoft/azure-percept-advanced-development/secured_locker
Author: Microsoft Corporation
Author-email: SCZAIMLDataProtect@microsoft.com
License: MIT License
Platform: UNKNOWN
Classifier: Programming Language :: Python :: 3
Classifier: Programming Language :: Python :: 3.6
Classifier: Programming Language :: Python :: 3.7
Classifier: License :: OSI Approved :: MIT License
Classifier: Operating System :: OS Independent
Requires-Dist: pycryptodome (>=3.9.8)
Requires-Dist: requests (>=2.24.0)
Requires-Dist: azure-keyvault-secrets (>=4.2.0)
Requires-Dist: azure-core (>=1.8.0)
Requires-Dist: azure-identity (<1.3.0,>=1.2.0)
Requires-Dist: cryptography (>=3.2)
Requires-Dist: adal (>=1.2.4)
Requires-Dist: PyJWT (>=1.7.1)
Requires-Dist: opentelemetry-api (==0.15b0)
Requires-Dist: opentelemetry-sdk (==0.15b0)
Provides-Extra: dev
Requires-Dist: pytest (>=3.7) ; extra == 'dev'
